[
  {
    "source": "British Council",
    "title": "A1-A2 Grammar",
    "url": "https://learnenglish.britishcouncil.org/grammar/a1-a2-grammar",
    "error": "HTTPSConnectionPool(host='learnenglish.britishcouncil.org', port=443): Read timed out. (read timeout=30)"
  },
  {
    "source": "British Council",
    "title": "B1-B2 Grammar",
    "url": "https://learnenglish.britishcouncil.org/grammar/b1-b2-grammar",
    "error": "HTTPSConnectionPool(host='learnenglish.britishcouncil.org', port=443): Read timed out. (read timeout=30)"
  },
  {
    "source": "British Council",
    "title": "C1-C2 Grammar",
    "url": "https://learnenglish.britishcouncil.org/grammar/c1-c2-grammar",
    "error": "HTTPSConnectionPool(host='learnenglish.britishcouncil.org', port=443): Read timed out. (read timeout=30)"
  }
]
